Metadata-Version: 2.1
Name: pyis
Version: 1.9.3
Summary: A library to check your values in your projects
Home-page: https://github.com/BlackIQ/pyis
Author: Amirhossein Mohammadi
Author-email: amirhosseinmohammadi1380@yahoo.com
License: MIT
Platform: UNKNOWN
